{
  "spreadsheet_id": "1inBUyjKQbFEH1tt-XnauWFKJqRU21F-GQGEzleLJLbA",
  "spreadsheet_title": "★新【EB塾】【2026年度】指導モニタリング管理表",
  "index": 7,
  "gid": 1493251394,
  "title": "70161 坂本さま",
  "grid_properties": {
    "rowCount": 1008,
    "columnCount": 26
  },
  "merged_ranges": [
    {
      "sheetId": 1493251394,
      "startRowIndex": 44,
      "endRowIndex": 45,
      "startColumnIndex": 7,
      "endColumnIndex": 9
    },
    {
      "sheetId": 1493251394,
      "startRowIndex": 44,
      "endRowIndex": 45,
      "startColumnIndex": 9,
      "endColumnIndex": 15
    },
    {
      "sheetId": 1493251394,
      "startRowIndex": 42,
      "endRowIndex": 43,
      "startColumnIndex": 2,
      "endColumnIndex": 7
    },
    {
      "sheetId": 1493251394,
      "startRowIndex": 42,
      "endRowIndex": 43,
      "startColumnIndex": 7,
      "endColumnIndex": 9
    },
    {
      "sheetId": 1493251394,
      "startRowIndex": 42,
      "endRowIndex": 43,
      "startColumnIndex": 9,
      "endColumnIndex": 15
    },
    {
      "sheetId": 1493251394,
      "startRowIndex": 43,
      "endRowIndex": 44,
      "startColumnIndex": 2,
      "endColumnIndex": 7
    },
    {
      "sheetId": 1493251394,
      "startRowIndex": 43,
      "endRowIndex": 44,
      "startColumnIndex": 7,
      "endColumnIndex": 9
    },
    {
      "sheetId": 1493251394,
      "startRowIndex": 43,
      "endRowIndex": 44,
      "startColumnIndex": 9,
      "endColumnIndex": 15
    },
    {
      "sheetId": 1493251394,
      "startRowIndex": 44,
      "endRowIndex": 45,
      "startColumnIndex": 2,
      "endColumnIndex": 7
    },
    {
      "sheetId": 1493251394,
      "startRowIndex": 47,
      "endRowIndex": 48,
      "startColumnIndex": 7,
      "endColumnIndex": 9
    },
    {
      "sheetId": 1493251394,
      "startRowIndex": 47,
      "endRowIndex": 48,
      "startColumnIndex": 9,
      "endColumnIndex": 15
    },
    {
      "sheetId": 1493251394,
      "startRowIndex": 45,
      "endRowIndex": 46,
      "startColumnIndex": 2,
      "endColumnIndex": 7
    },
    {
      "sheetId": 1493251394,
      "startRowIndex": 45,
      "endRowIndex": 46,
      "startColumnIndex": 7,
      "endColumnIndex": 9
    },
    {
      "sheetId": 1493251394,
      "startRowIndex": 45,
      "endRowIndex": 46,
      "startColumnIndex": 9,
      "endColumnIndex": 15
    },
    {
      "sheetId": 1493251394,
      "startRowIndex": 46,
      "endRowIndex": 47,
      "startColumnIndex": 2,
      "endColumnIndex": 7
    },
    {
      "sheetId": 1493251394,
      "startRowIndex": 46,
      "endRowIndex": 47,
      "startColumnIndex": 7,
      "endColumnIndex": 9
    },
    {
      "sheetId": 1493251394,
      "startRowIndex": 46,
      "endRowIndex": 47,
      "startColumnIndex": 9,
      "endColumnIndex": 15
    },
    {
      "sheetId": 1493251394,
      "startRowIndex": 47,
      "endRowIndex": 48,
      "startColumnIndex": 2,
      "endColumnIndex": 7
    },
    {
      "sheetId": 1493251394,
      "startRowIndex": 12,
      "endRowIndex": 14,
      "startColumnIndex": 1,
      "endColumnIndex": 2
    },
    {
      "sheetId": 1493251394,
      "startRowIndex": 17,
      "endRowIndex": 21,
      "startColumnIndex": 1,
      "endColumnIndex": 2
    },
    {
      "sheetId": 1493251394,
      "startRowIndex": 24,
      "endRowIndex": 28,
      "startColumnIndex": 1,
      "endColumnIndex": 2
    },
    {
      "sheetId": 1493251394,
      "startRowIndex": 31,
      "endRowIndex": 34,
      "startColumnIndex": 1,
      "endColumnIndex": 2
    },
    {
      "sheetId": 1493251394,
      "startRowIndex": 3,
      "endRowIndex": 4,
      "startColumnIndex": 4,
      "endColumnIndex": 6
    },
    {
      "sheetId": 1493251394,
      "startRowIndex": 6,
      "endRowIndex": 7,
      "startColumnIndex": 3,
      "endColumnIndex": 5
    },
    {
      "sheetId": 1493251394,
      "startRowIndex": 6,
      "endRowIndex": 7,
      "startColumnIndex": 5,
      "endColumnIndex": 7
    },
    {
      "sheetId": 1493251394,
      "startRowIndex": 6,
      "endRowIndex": 7,
      "startColumnIndex": 7,
      "endColumnIndex": 9
    },
    {
      "sheetId": 1493251394,
      "startRowIndex": 7,
      "endRowIndex": 8,
      "startColumnIndex": 9,
      "endColumnIndex": 11
    },
    {
      "sheetId": 1493251394,
      "startRowIndex": 10,
      "endRowIndex": 11,
      "startColumnIndex": 3,
      "endColumnIndex": 15
    },
    {
      "sheetId": 1493251394,
      "startRowIndex": 15,
      "endRowIndex": 16,
      "startColumnIndex": 3,
      "endColumnIndex": 15
    },
    {
      "sheetId": 1493251394,
      "startRowIndex": 38,
      "endRowIndex": 39,
      "startColumnIndex": 7,
      "endColumnIndex": 9
    },
    {
      "sheetId": 1493251394,
      "startRowIndex": 38,
      "endRowIndex": 39,
      "startColumnIndex": 9,
      "endColumnIndex": 15
    },
    {
      "sheetId": 1493251394,
      "startRowIndex": 19,
      "endRowIndex": 20,
      "startColumnIndex": 4,
      "endColumnIndex": 8
    },
    {
      "sheetId": 1493251394,
      "startRowIndex": 22,
      "endRowIndex": 23,
      "startColumnIndex": 3,
      "endColumnIndex": 15
    },
    {
      "sheetId": 1493251394,
      "startRowIndex": 29,
      "endRowIndex": 30,
      "startColumnIndex": 3,
      "endColumnIndex": 15
    },
    {
      "sheetId": 1493251394,
      "startRowIndex": 37,
      "endRowIndex": 38,
      "startColumnIndex": 2,
      "endColumnIndex": 7
    },
    {
      "sheetId": 1493251394,
      "startRowIndex": 37,
      "endRowIndex": 38,
      "startColumnIndex": 7,
      "endColumnIndex": 9
    },
    {
      "sheetId": 1493251394,
      "startRowIndex": 37,
      "endRowIndex": 38,
      "startColumnIndex": 9,
      "endColumnIndex": 15
    },
    {
      "sheetId": 1493251394,
      "startRowIndex": 38,
      "endRowIndex": 39,
      "startColumnIndex": 2,
      "endColumnIndex": 7
    },
    {
      "sheetId": 1493251394,
      "startRowIndex": 41,
      "endRowIndex": 42,
      "startColumnIndex": 7,
      "endColumnIndex": 9
    },
    {
      "sheetId": 1493251394,
      "startRowIndex": 41,
      "endRowIndex": 42,
      "startColumnIndex": 9,
      "endColumnIndex": 15
    },
    {
      "sheetId": 1493251394,
      "startRowIndex": 39,
      "endRowIndex": 40,
      "startColumnIndex": 2,
      "endColumnIndex": 7
    },
    {
      "sheetId": 1493251394,
      "startRowIndex": 39,
      "endRowIndex": 40,
      "startColumnIndex": 7,
      "endColumnIndex": 9
    },
    {
      "sheetId": 1493251394,
      "startRowIndex": 39,
      "endRowIndex": 40,
      "startColumnIndex": 9,
      "endColumnIndex": 15
    },
    {
      "sheetId": 1493251394,
      "startRowIndex": 40,
      "endRowIndex": 41,
      "startColumnIndex": 2,
      "endColumnIndex": 7
    },
    {
      "sheetId": 1493251394,
      "startRowIndex": 40,
      "endRowIndex": 41,
      "startColumnIndex": 7,
      "endColumnIndex": 9
    },
    {
      "sheetId": 1493251394,
      "startRowIndex": 40,
      "endRowIndex": 41,
      "startColumnIndex": 9,
      "endColumnIndex": 15
    },
    {
      "sheetId": 1493251394,
      "startRowIndex": 41,
      "endRowIndex": 42,
      "startColumnIndex": 2,
      "endColumnIndex": 7
    },
    {
      "sheetId": 1493251394,
      "startRowIndex": 50,
      "endRowIndex": 51,
      "startColumnIndex": 7,
      "endColumnIndex": 9
    },
    {
      "sheetId": 1493251394,
      "startRowIndex": 50,
      "endRowIndex": 51,
      "startColumnIndex": 9,
      "endColumnIndex": 15
    },
    {
      "sheetId": 1493251394,
      "startRowIndex": 48,
      "endRowIndex": 49,
      "startColumnIndex": 2,
      "endColumnIndex": 7
    },
    {
      "sheetId": 1493251394,
      "startRowIndex": 48,
      "endRowIndex": 49,
      "startColumnIndex": 7,
      "endColumnIndex": 9
    },
    {
      "sheetId": 1493251394,
      "startRowIndex": 48,
      "endRowIndex": 49,
      "startColumnIndex": 9,
      "endColumnIndex": 15
    },
    {
      "sheetId": 1493251394,
      "startRowIndex": 49,
      "endRowIndex": 50,
      "startColumnIndex": 2,
      "endColumnIndex": 7
    },
    {
      "sheetId": 1493251394,
      "startRowIndex": 49,
      "endRowIndex": 50,
      "startColumnIndex": 7,
      "endColumnIndex": 9
    },
    {
      "sheetId": 1493251394,
      "startRowIndex": 49,
      "endRowIndex": 50,
      "startColumnIndex": 9,
      "endColumnIndex": 15
    },
    {
      "sheetId": 1493251394,
      "startRowIndex": 50,
      "endRowIndex": 51,
      "startColumnIndex": 2,
      "endColumnIndex": 7
    }
  ],
  "values": [
    [],
    [
      "★EB塾生徒一覧 へ戻る",
      "生徒情報"
    ],
    [
      "生徒カルテ",
      "生徒番号",
      "生徒氏名",
      "学年",
      "最終試験時期"
    ],
    [
      "学習計画",
      "70161",
      "坂本 圭杜",
      "高１",
      "2027年11月"
    ],
    [],
    [
      "",
      "選考情報"
    ],
    [
      "",
      "No",
      "選考番号",
      "採用教師名",
      "",
      "指導コース",
      "",
      "指導科目",
      "",
      "契約時間（月）"
    ],
    [
      "",
      "1"
    ],
    [],
    [
      "",
      "契約時間充足率"
    ],
    [
      "",
      "",
      "",
      "2026年度　（月）"
    ],
    [
      "",
      "選考番号",
      "契約時間充足率",
      "4",
      "5",
      "6",
      "7",
      "8",
      "9",
      "10",
      "11",
      "12",
      "1",
      "2",
      "3"
    ],
    [
      "",
      "",
      "実施時間"
    ],
    [
      "",
      "",
      "契約時間充足率"
    ],
    [],
    [
      "",
      "教師評価",
      "",
      "2026年度　（月）"
    ],
    [
      "",
      "選考番号",
      "教師評価",
      "4",
      "5",
      "6",
      "7",
      "8",
      "9",
      "10",
      "11",
      "12",
      "1",
      "2",
      "3"
    ],
    [
      "",
      "",
      "指導の計画性"
    ],
    [
      "",
      "",
      "指導の計画性"
    ],
    [
      "",
      "",
      "指導キャンセル"
    ],
    [
      "",
      "",
      "総合満足度"
    ],
    [],
    [
      "",
      "指導報告書",
      "",
      "2026年度　（月）"
    ],
    [
      "",
      "選考番号",
      "指導報告書",
      "4",
      "5",
      "6",
      "7",
      "8",
      "9",
      "10",
      "11",
      "12",
      "1",
      "2",
      "3"
    ],
    [
      "",
      "",
      "メッセージの有無",
      "FALSE",
      "FALSE",
      "FALSE",
      "FALSE",
      "FALSE",
      "FALSE",
      "FALSE",
      "FALSE",
      "FALSE",
      "FALSE",
      "FALSE",
      "FALSE"
    ],
    [
      "",
      "",
      "課題の明確化",
      "FALSE",
      "FALSE",
      "FALSE",
      "FALSE",
      "FALSE",
      "FALSE",
      "FALSE",
      "FALSE",
      "FALSE",
      "FALSE",
      "FALSE",
      "FALSE"
    ],
    [
      "",
      "",
      "月次報告生徒達成度"
    ],
    [
      "",
      "",
      "月次報告教師達成度"
    ],
    [],
    [
      "",
      "学習進捗確認",
      "",
      "2026年度　（月）"
    ],
    [
      "",
      "選考番号",
      "学習進捗",
      "4",
      "5",
      "6",
      "7",
      "8",
      "9",
      "10",
      "11",
      "12",
      "1",
      "2",
      "3"
    ],
    [
      "",
      "",
      "計画の更新"
    ],
    [
      "",
      "",
      "計画の妥当性"
    ],
    [
      "",
      "",
      "ユニットテストのスコア"
    ],
    [],
    [],
    [],
    [
      "",
      "月",
      "三者面談",
      "",
      "",
      "",
      "",
      "三者面談面談実施日",
      "",
      "教師mtg",
      "",
      "",
      "",
      "",
      "",
      "教師mtg実施日"
    ],
    [
      "",
      "4",
      "ご家庭と三者面談実施。前半10分に学習進捗を確認。\n\n・学校の進捗：春休み前にAlgebraのBinomial theoremが完了。まだ新学期が始まっておらず、シラバスや教科書なし。\n・高1の3学期の成績：Math 7/7\n・学校の試験日程：5/29-6/3、8/28-9/2\n・部活：テニス部、ジャズアンサンブル部\n・指導時間：平日19:00または19:30開始を希望\n\n■2. 自己分析と英検対策\n・英検1級：\n　- 一次試験は合格、二次試験は不合格。\n　- 要因：トピックの解釈違い。\n　- 対策：語彙力強化、スピーチの録音チェック、冷静な読解を意識する。\n・興味・関心：\n　- 文学に強い関心。「飾らない自分、本当の自分と向き合える」プロセスに魅力を感じている。\n・自身の強み：\n　- 高い実行力と持続力。持久走（学年1位）のために1ヶ月前から毎日10km走るなど、目標達成への執着心が強い。\n\n■3. 進路探求（リベラルアーツ教育）\n・志望校：\n　- 国際基督教大学（ICU）の理念に強い関心。\n　- 他、慶應SFC、上智FLA、早稲田SILSなどを検討。\n・分析：\n　- 思考を深めるプロセスを重視するため、全編英語の環境より、日本語と英語を併用するバイリンガル環境（ICUやSFC等）との親和性が高い可能性。\n\n■4. 課外活動の活用\n・内容：\n　- 5年間継続している「レモネードスタンド」のボランティア活動。\n　- プロバスケットボールチームや飲料会社との提携を含む。\n・今後の活用：\n　- 単なる「募金活動」としてだけでなく、提携の仕組みや運営プロセスを言語化し、AO入試等のアピール材料として深掘りする。\n\n■5. 次回へのアクションアイテム\n【坂本様】\n・将来やりたいこと、興味のある分野のさらなる深掘り。\n・ICUのカリキュラムや適合性のリサーチ。\n・新学期の時間割確定後、次回面談の予約。\n\n【元山様】\n・前担当（松浦先生）への指導終了連絡。\n・新講師の授業時間（19時/19時半開始）の最終確認。\n\n【岡部様】\n・坂本様の特性に合うリベラルアーツ系大学のリストアップと提案。\n・次回面談用の予約リンク送付。",
      "",
      "",
      "",
      "",
      "2026/04/06"
    ],
    [
      "",
      "5"
    ],
    [
      "",
      "6"
    ],
    [
      "",
      "7"
    ],
    [
      "",
      "8"
    ],
    [
      "",
      "9"
    ],
    [
      "",
      "10"
    ],
    [
      "",
      "11"
    ],
    [
      "",
      "12"
    ],
    [
      "",
      "1"
    ],
    [
      "",
      "2"
    ],
    [
      "",
      "3"
    ],
    [
      "",
      "3"
    ]
  ]
}