{
  "properties": {
    "autoRecalc": "ON_CHANGE",
    "defaultFormat": {
      "backgroundColor": {
        "blue": 1,
        "green": 1,
        "red": 1
      },
      "backgroundColorStyle": {
        "rgbColor": {
          "blue": 1,
          "green": 1,
          "red": 1
        }
      },
      "padding": {
        "bottom": 2,
        "left": 3,
        "right": 3,
        "top": 2
      },
      "textFormat": {
        "bold": false,
        "fontFamily": "arial,sans,sans-serif",
        "fontSize": 10,
        "foregroundColor": {},
        "foregroundColorStyle": {
          "rgbColor": {}
        },
        "italic": false,
        "strikethrough": false,
        "underline": false
      },
      "verticalAlignment": "BOTTOM",
      "wrapStrategy": "OVERFLOW_CELL"
    },
    "locale": "ja_JP",
    "spreadsheetTheme": {
      "primaryFontFamily": "Arial",
      "themeColors": [
        {
          "color": {
            "rgbColor": {}
          },
          "colorType": "TEXT"
        },
        {
          "color": {
            "rgbColor": {
              "blue": 1,
              "green": 1,
              "red": 1
            }
          },
          "colorType": "BACKGROUND"
        },
        {
          "color": {
            "rgbColor": {
              "blue": 0.95686275,
              "green": 0.52156866,
              "red": 0.25882354
            }
          },
          "colorType": "ACCENT1"
        },
        {
          "color": {
            "rgbColor": {
              "blue": 0.20784314,
              "green": 0.2627451,
              "red": 0.91764706
            }
          },
          "colorType": "ACCENT2"
        },
        {
          "color": {
            "rgbColor": {
              "blue": 0.015686275,
              "green": 0.7372549,
              "red": 0.9843137
            }
          },
          "colorType": "ACCENT3"
        },
        {
          "color": {
            "rgbColor": {
              "blue": 0.3254902,
              "green": 0.65882355,
              "red": 0.20392157
            }
          },
          "colorType": "ACCENT4"
        },
        {
          "color": {
            "rgbColor": {
              "blue": 0.003921569,
              "green": 0.42745098,
              "red": 1
            }
          },
          "colorType": "ACCENT5"
        },
        {
          "color": {
            "rgbColor": {
              "blue": 0.7764706,
              "green": 0.7411765,
              "red": 0.27450982
            }
          },
          "colorType": "ACCENT6"
        },
        {
          "color": {
            "rgbColor": {
              "blue": 0.8,
              "green": 0.33333334,
              "red": 0.06666667
            }
          },
          "colorType": "LINK"
        }
      ]
    },
    "timeZone": "Asia/Tokyo",
    "title": "67982 平林さま　学習計画表Physics(SL) "
  },
  "sheets": [
    {
      "properties": {
        "gridProperties": {
          "columnCount": 26,
          "rowCount": 1002
        },
        "index": 0,
        "sheetId": 1718767612,
        "sheetType": "GRID",
        "title": "student"
      }
    },
    {
      "merges": [
        {
          "endColumnIndex": 2,
          "endRowIndex": 1,
          "sheetId": 704050348,
          "startColumnIndex": 0,
          "startRowIndex": 0
        },
        {
          "endColumnIndex": 2,
          "endRowIndex": 16,
          "sheetId": 704050348,
          "startColumnIndex": 0,
          "startRowIndex": 15
        },
        {
          "endColumnIndex": 2,
          "endRowIndex": 29,
          "sheetId": 704050348,
          "startColumnIndex": 0,
          "startRowIndex": 28
        },
        {
          "endColumnIndex": 2,
          "endRowIndex": 38,
          "sheetId": 704050348,
          "startColumnIndex": 0,
          "startRowIndex": 37
        },
        {
          "endColumnIndex": 2,
          "endRowIndex": 46,
          "sheetId": 704050348,
          "startColumnIndex": 0,
          "startRowIndex": 45
        },
        {
          "endColumnIndex": 2,
          "endRowIndex": 60,
          "sheetId": 704050348,
          "startColumnIndex": 0,
          "startRowIndex": 58
        }
      ],
      "properties": {
        "gridProperties": {
          "columnCount": 29,
          "rowCount": 1017
        },
        "index": 1,
        "sheetId": 704050348,
        "sheetType": "GRID",
        "title": "lesson plan"
      }
    },
    {
      "properties": {
        "gridProperties": {
          "columnCount": 59,
          "rowCount": 1006
        },
        "hidden": true,
        "index": 2,
        "sheetId": 1727797645,
        "sheetType": "GRID",
        "title": "（非表示）トピック一覧"
      }
    },
    {
      "bandedRanges": [
        {
          "bandedRangeId": 137145717,
          "bandedRangeReference": "137145717",
          "range": {
            "endColumnIndex": 17,
            "endRowIndex": 1,
            "sheetId": 661355791,
            "startColumnIndex": 12,
            "startRowIndex": 0
          },
          "rowProperties": {
            "firstBandColor": {
              "blue": 1,
              "green": 1,
              "red": 1
            },
            "firstBandColorStyle": {
              "rgbColor": {
                "blue": 1,
                "green": 1,
                "red": 1
              }
            },
            "headerColor": {
              "blue": 0.23529412,
              "green": 0.27450982,
              "red": 0.73333335
            },
            "headerColorStyle": {
              "rgbColor": {
                "blue": 0.23529412,
                "green": 0.27450982,
                "red": 0.73333335
              }
            },
            "secondBandColor": {
              "blue": 0.98039216,
              "green": 0.9764706,
              "red": 0.972549
            },
            "secondBandColorStyle": {
              "rgbColor": {
                "blue": 0.98039216,
                "green": 0.9764706,
                "red": 0.972549
              }
            }
          }
        },
        {
          "bandedRangeId": 2056664546,
          "bandedRangeReference": "2056664546",
          "range": {
            "endColumnIndex": 5,
            "endRowIndex": 1,
            "sheetId": 661355791,
            "startColumnIndex": 0,
            "startRowIndex": 0
          },
          "rowProperties": {
            "firstBandColor": {
              "blue": 1,
              "green": 1,
              "red": 1
            },
            "firstBandColorStyle": {
              "rgbColor": {
                "blue": 1,
                "green": 1,
                "red": 1
              }
            },
            "headerColor": {
              "blue": 0.32941177,
              "green": 0.40784314,
              "red": 0.20784314
            },
            "headerColorStyle": {
              "rgbColor": {
                "blue": 0.32941177,
                "green": 0.40784314,
                "red": 0.20784314
              }
            },
            "secondBandColor": {
              "blue": 0.98039216,
              "green": 0.9764706,
              "red": 0.972549
            },
            "secondBandColorStyle": {
              "rgbColor": {
                "blue": 0.98039216,
                "green": 0.9764706,
                "red": 0.972549
              }
            }
          }
        },
        {
          "bandedRangeId": 775306426,
          "bandedRangeReference": "775306426",
          "range": {
            "endColumnIndex": 11,
            "endRowIndex": 1,
            "sheetId": 661355791,
            "startColumnIndex": 6,
            "startRowIndex": 0
          },
          "rowProperties": {
            "firstBandColor": {
              "blue": 1,
              "green": 1,
              "red": 1
            },
            "firstBandColorStyle": {
              "rgbColor": {
                "blue": 1,
                "green": 1,
                "red": 1
              }
            },
            "headerColor": {
              "blue": 0.75686276,
              "green": 0.37254903,
              "red": 0.3254902
            },
            "headerColorStyle": {
              "rgbColor": {
                "blue": 0.75686276,
                "green": 0.37254903,
                "red": 0.3254902
              }
            },
            "secondBandColor": {
              "blue": 0.98039216,
              "green": 0.9764706,
              "red": 0.972549
            },
            "secondBandColorStyle": {
              "rgbColor": {
                "blue": 0.98039216,
                "green": 0.9764706,
                "red": 0.972549
              }
            }
          }
        },
        {
          "bandedRangeId": 2028609595,
          "range": {
            "endColumnIndex": 29,
            "endRowIndex": 1,
            "sheetId": 661355791,
            "startColumnIndex": 24,
            "startRowIndex": 0
          },
          "rowProperties": {
            "firstBandColor": {
              "blue": 1,
              "green": 1,
              "red": 1
            },
            "firstBandColorStyle": {
              "rgbColor": {
                "blue": 1,
                "green": 1,
                "red": 1
              }
            },
            "headerColor": {
              "blue": 0.25882354,
              "green": 0.21176471,
              "red": 0.60784316
            },
            "headerColorStyle": {
              "rgbColor": {
                "blue": 0.25882354,
                "green": 0.21176471,
                "red": 0.60784316
              }
            },
            "secondBandColor": {
              "blue": 0.98039216,
              "green": 0.9764706,
              "red": 0.972549
            },
            "secondBandColorStyle": {
              "rgbColor": {
                "blue": 0.98039216,
                "green": 0.9764706,
                "red": 0.972549
              }
            }
          }
        },
        {
          "bandedRangeId": 793604491,
          "bandedRangeReference": "793604491",
          "range": {
            "endColumnIndex": 23,
            "endRowIndex": 1,
            "sheetId": 661355791,
            "startColumnIndex": 18,
            "startRowIndex": 0
          },
          "rowProperties": {
            "firstBandColor": {
              "blue": 1,
              "green": 1,
              "red": 1
            },
            "firstBandColorStyle": {
              "rgbColor": {
                "blue": 1,
                "green": 1,
                "red": 1
              }
            },
            "headerColor": {
              "blue": 0.25882354,
              "green": 0.21176471,
              "red": 0.60784316
            },
            "headerColorStyle": {
              "rgbColor": {
                "blue": 0.25882354,
                "green": 0.21176471,
                "red": 0.60784316
              }
            },
            "secondBandColor": {
              "blue": 0.98039216,
              "green": 0.9764706,
              "red": 0.972549
            },
            "secondBandColorStyle": {
              "rgbColor": {
                "blue": 0.98039216,
                "green": 0.9764706,
                "red": 0.972549
              }
            }
          }
        },
        {
          "bandedRangeId": 1182522733,
          "range": {
            "endColumnIndex": 5,
            "endRowIndex": 17,
            "sheetId": 661355791,
            "startColumnIndex": 3,
            "startRowIndex": 1
          },
          "rowProperties": {
            "firstBandColor": {
              "blue": 1,
              "green": 1,
              "red": 1
            },
            "firstBandColorStyle": {
              "rgbColor": {
                "blue": 1,
                "green": 1,
                "red": 1
              }
            },
            "secondBandColor": {
              "blue": 0.98039216,
              "green": 0.9764706,
              "red": 0.972549
            },
            "secondBandColorStyle": {
              "rgbColor": {
                "blue": 0.98039216,
                "green": 0.9764706,
                "red": 0.972549
              }
            }
          }
        },
        {
          "bandedRangeId": 1203340590,
          "range": {
            "endColumnIndex": 29,
            "endRowIndex": 31,
            "sheetId": 661355791,
            "startColumnIndex": 27,
            "startRowIndex": 1
          },
          "rowProperties": {
            "firstBandColor": {
              "blue": 1,
              "green": 1,
              "red": 1
            },
            "firstBandColorStyle": {
              "rgbColor": {
                "blue": 1,
                "green": 1,
                "red": 1
              }
            },
            "secondBandColor": {
              "blue": 0.98039216,
              "green": 0.9764706,
              "red": 0.972549
            },
            "secondBandColorStyle": {
              "rgbColor": {
                "blue": 0.98039216,
                "green": 0.9764706,
                "red": 0.972549
              }
            }
          }
        },
        {
          "bandedRangeId": 1248355489,
          "range": {
            "endColumnIndex": 5,
            "endRowIndex": 30,
            "sheetId": 661355791,
            "startColumnIndex": 3,
            "startRowIndex": 25
          },
          "rowProperties": {
            "firstBandColor": {
              "blue": 1,
              "green": 1,
              "red": 1
            },
            "firstBandColorStyle": {
              "rgbColor": {
                "blue": 1,
                "green": 1,
                "red": 1
              }
            },
            "secondBandColor": {
              "blue": 0.98039216,
              "green": 0.9764706,
              "red": 0.972549
            },
            "secondBandColorStyle": {
              "rgbColor": {
                "blue": 0.98039216,
                "green": 0.9764706,
                "red": 0.972549
              }
            }
          }
        },
        {
          "bandedRangeId": 1506770841,
          "range": {
            "endColumnIndex": 11,
            "endRowIndex": 31,
            "sheetId": 661355791,
            "startColumnIndex": 9,
            "startRowIndex": 1
          },
          "rowProperties": {
            "firstBandColor": {
              "blue": 1,
              "green": 1,
              "red": 1
            },
            "firstBandColorStyle": {
              "rgbColor": {
                "blue": 1,
                "green": 1,
                "red": 1
              }
            },
            "secondBandColor": {
              "blue": 0.98039216,
              "green": 0.9764706,
              "red": 0.972549
            },
            "secondBandColorStyle": {
              "rgbColor": {
                "blue": 0.98039216,
                "green": 0.9764706,
                "red": 0.972549
              }
            }
          }
        },
        {
          "bandedRangeId": 1862286728,
          "range": {
            "endColumnIndex": 23,
            "endRowIndex": 22,
            "sheetId": 661355791,
            "startColumnIndex": 21,
            "startRowIndex": 1
          },
          "rowProperties": {
            "firstBandColor": {
              "blue": 1,
              "green": 1,
              "red": 1
            },
            "firstBandColorStyle": {
              "rgbColor": {
                "blue": 1,
                "green": 1,
                "red": 1
              }
            },
            "secondBandColor": {
              "blue": 0.98039216,
              "green": 0.9764706,
              "red": 0.972549
            },
            "secondBandColorStyle": {
              "rgbColor": {
                "blue": 0.98039216,
                "green": 0.9764706,
                "red": 0.972549
              }
            }
          }
        },
        {
          "bandedRangeId": 1965044031,
          "range": {
            "endColumnIndex": 17,
            "endRowIndex": 16,
            "sheetId": 661355791,
            "startColumnIndex": 15,
            "startRowIndex": 1
          },
          "rowProperties": {
            "firstBandColor": {
              "blue": 1,
              "green": 1,
              "red": 1
            },
            "firstBandColorStyle": {
              "rgbColor": {
                "blue": 1,
                "green": 1,
                "red": 1
              }
            },
            "secondBandColor": {
              "blue": 0.98039216,
              "green": 0.9764706,
              "red": 0.972549
            },
            "secondBandColorStyle": {
              "rgbColor": {
                "blue": 0.98039216,
                "green": 0.9764706,
                "red": 0.972549
              }
            }
          }
        },
        {
          "bandedRangeId": 205867291,
          "range": {
            "endColumnIndex": 11,
            "endRowIndex": 35,
            "sheetId": 661355791,
            "startColumnIndex": 10,
            "startRowIndex": 31
          },
          "rowProperties": {
            "firstBandColor": {
              "blue": 1,
              "green": 1,
              "red": 1
            },
            "firstBandColorStyle": {
              "rgbColor": {
                "blue": 1,
                "green": 1,
                "red": 1
              }
            },
            "secondBandColor": {
              "blue": 0.98039216,
              "green": 0.9764706,
              "red": 0.972549
            },
            "secondBandColorStyle": {
              "rgbColor": {
                "blue": 0.98039216,
                "green": 0.9764706,
                "red": 0.972549
              }
            }
          }
        }
      ],
      "conditionalFormats": [
        {
          "booleanRule": {
            "condition": {
              "type": "TEXT_CONTAINS",
              "values": [
                {
                  "userEnteredValue": "未定"
                }
              ]
            },
            "format": {
              "textFormat": {
                "foregroundColor": {
                  "blue": 0.23529412,
                  "green": 0.27450982,
                  "red": 0.73333335
                },
                "foregroundColorStyle": {
                  "rgbColor": {
                    "blue": 0.23529412,
                    "green": 0.27450982,
                    "red": 0.73333335
                  }
                }
              }
            }
          },
          "ranges": [
            {
              "endColumnIndex": 1,
              "endRowIndex": 34,
              "sheetId": 661355791,
              "startColumnIndex": 0,
              "startRowIndex": 33
            },
            {
              "endColumnIndex": 2,
              "endRowIndex": 67,
              "sheetId": 661355791,
              "startColumnIndex": 1,
              "startRowIndex": 33
            }
          ]
        },
        {
          "booleanRule": {
            "condition": {
              "type": "TEXT_CONTAINS",
              "values": [
                {
                  "userEnteredValue": "未定"
                }
              ]
            },
            "format": {
              "textFormat": {
                "foregroundColor": {
                  "blue": 0.23529412,
                  "green": 0.27450982,
                  "red": 0.73333335
                },
                "foregroundColorStyle": {
                  "rgbColor": {
                    "blue": 0.23529412,
                    "green": 0.27450982,
                    "red": 0.73333335
                  }
                }
              }
            }
          },
          "ranges": [
            {
              "endColumnIndex": 14,
              "endRowIndex": 26,
              "sheetId": 661355791,
              "startColumnIndex": 13,
              "startRowIndex": 16
            }
          ]
        },
        {
          "booleanRule": {
            "condition": {
              "type": "TEXT_CONTAINS",
              "values": [
                {
                  "userEnteredValue": "未定"
                }
              ]
            },
            "format": {
              "textFormat": {
                "foregroundColor": {
                  "blue": 0.23529412,
                  "green": 0.27450982,
                  "red": 0.73333335
                },
                "foregroundColorStyle": {
                  "rgbColor": {
                    "blue": 0.23529412,
                    "green": 0.27450982,
                    "red": 0.73333335
                  }
                }
              }
            }
          },
          "ranges": [
            {
              "endColumnIndex": 26,
              "endRowIndex": 22,
              "sheetId": 661355791,
              "startColumnIndex": 25,
              "startRowIndex": 11
            },
            {
              "endColumnIndex": 20,
              "endRowIndex": 28,
              "sheetId": 661355791,
              "startColumnIndex": 19,
              "startRowIndex": 22
            }
          ]
        }
      ],
      "merges": [
        {
          "endColumnIndex": 26,
          "endRowIndex": 23,
          "sheetId": 661355791,
          "startColumnIndex": 25,
          "startRowIndex": 19
        },
        {
          "endColumnIndex": 26,
          "endRowIndex": 29,
          "sheetId": 661355791,
          "startColumnIndex": 25,
          "startRowIndex": 23
        },
        {
          "endColumnIndex": 26,
          "endRowIndex": 35,
          "sheetId": 661355791,
          "startColumnIndex": 25,
          "startRowIndex": 29
        },
        {
          "endColumnIndex": 26,
          "endRowIndex": 44,
          "sheetId": 661355791,
          "startColumnIndex": 25,
          "startRowIndex": 35
        },
        {
          "endColumnIndex": 20,
          "endRowIndex": 8,
          "sheetId": 661355791,
          "startColumnIndex": 19,
          "startRowIndex": 1
        },
        {
          "endColumnIndex": 25,
          "endRowIndex": 44,
          "sheetId": 661355791,
          "startColumnIndex": 24,
          "startRowIndex": 1
        },
        {
          "endColumnIndex": 26,
          "endRowIndex": 6,
          "sheetId": 661355791,
          "startColumnIndex": 25,
          "startRowIndex": 1
        },
        {
          "endColumnIndex": 26,
          "endRowIndex": 11,
          "sheetId": 661355791,
          "startColumnIndex": 25,
          "startRowIndex": 6
        },
        {
          "endColumnIndex": 20,
          "endRowIndex": 13,
          "sheetId": 661355791,
          "startColumnIndex": 19,
          "startRowIndex": 8
        },
        {
          "endColumnIndex": 26,
          "endRowIndex": 19,
          "sheetId": 661355791,
          "startColumnIndex": 25,
          "startRowIndex": 11
        },
        {
          "endColumnIndex": 20,
          "endRowIndex": 16,
          "sheetId": 661355791,
          "startColumnIndex": 19,
          "startRowIndex": 13
        },
        {
          "endColumnIndex": 2,
          "endRowIndex": 5,
          "sheetId": 661355791,
          "startColumnIndex": 1,
          "startRowIndex": 1
        },
        {
          "endColumnIndex": 2,
          "endRowIndex": 33,
          "sheetId": 661355791,
          "startColumnIndex": 1,
          "startRowIndex": 29
        },
        {
          "endColumnIndex": 8,
          "endRowIndex": 32,
          "sheetId": 661355791,
          "startColumnIndex": 7,
          "startRowIndex": 29
        },
        {
          "endColumnIndex": 8,
          "endRowIndex": 35,
          "sheetId": 661355791,
          "startColumnIndex": 7,
          "startRowIndex": 32
        },
        {
          "endColumnIndex": 1,
          "endRowIndex": 33,
          "sheetId": 661355791,
          "startColumnIndex": 0,
          "startRowIndex": 1
        },
        {
          "endColumnIndex": 7,
          "endRowIndex": 35,
          "sheetId": 661355791,
          "startColumnIndex": 6,
          "startRowIndex": 1
        },
        {
          "endColumnIndex": 8,
          "endRowIndex": 6,
          "sheetId": 661355791,
          "startColumnIndex": 7,
          "startRowIndex": 1
        },
        {
          "endColumnIndex": 19,
          "endRowIndex": 22,
          "sheetId": 661355791,
          "startColumnIndex": 18,
          "startRowIndex": 1
        },
        {
          "endColumnIndex": 8,
          "endRowIndex": 23,
          "sheetId": 661355791,
          "startColumnIndex": 7,
          "startRowIndex": 18
        },
        {
          "endColumnIndex": 8,
          "endRowIndex": 26,
          "sheetId": 661355791,
          "startColumnIndex": 7,
          "startRowIndex": 23
        },
        {
          "endColumnIndex": 8,
          "endRowIndex": 29,
          "sheetId": 661355791,
          "startColumnIndex": 7,
          "startRowIndex": 26
        },
        {
          "endColumnIndex": 14,
          "endRowIndex": 5,
          "sheetId": 661355791,
          "startColumnIndex": 13,
          "startRowIndex": 1
        },
        {
          "endColumnIndex": 14,
          "endRowIndex": 8,
          "sheetId": 661355791,
          "startColumnIndex": 13,
          "startRowIndex": 5
        },
        {
          "endColumnIndex": 13,
          "endRowIndex": 16,
          "sheetId": 661355791,
          "startColumnIndex": 12,
          "startRowIndex": 1
        },
        {
          "endColumnIndex": 14,
          "endRowIndex": 10,
          "sheetId": 661355791,
          "startColumnIndex": 13,
          "startRowIndex": 8
        },
        {
          "endColumnIndex": 14,
          "endRowIndex": 13,
          "sheetId": 661355791,
          "startColumnIndex": 13,
          "startRowIndex": 10
        },
        {
          "endColumnIndex": 14,
          "endRowIndex": 16,
          "sheetId": 661355791,
          "startColumnIndex": 13,
          "startRowIndex": 13
        },
        {
          "endColumnIndex": 8,
          "endRowIndex": 12,
          "sheetId": 661355791,
          "startColumnIndex": 7,
          "startRowIndex": 6
        },
        {
          "endColumnIndex": 8,
          "endRowIndex": 18,
          "sheetId": 661355791,
          "startColumnIndex": 7,
          "startRowIndex": 12
        },
        {
          "endColumnIndex": 2,
          "endRowIndex": 17,
          "sheetId": 661355791,
          "startColumnIndex": 1,
          "startRowIndex": 13
        },
        {
          "endColumnIndex": 2,
          "endRowIndex": 21,
          "sheetId": 661355791,
          "startColumnIndex": 1,
          "startRowIndex": 17
        },
        {
          "endColumnIndex": 20,
          "endRowIndex": 19,
          "sheetId": 661355791,
          "startColumnIndex": 19,
          "startRowIndex": 16
        },
        {
          "endColumnIndex": 20,
          "endRowIndex": 22,
          "sheetId": 661355791,
          "startColumnIndex": 19,
          "startRowIndex": 19
        },
        {
          "endColumnIndex": 2,
          "endRowIndex": 13,
          "sheetId": 661355791,
          "startColumnIndex": 1,
          "startRowIndex": 9
        },
        {
          "endColumnIndex": 2,
          "endRowIndex": 25,
          "sheetId": 661355791,
          "startColumnIndex": 1,
          "startRowIndex": 21
        },
        {
          "endColumnIndex": 2,
          "endRowIndex": 9,
          "sheetId": 661355791,
          "startColumnIndex": 1,
          "startRowIndex": 5
        },
        {
          "endColumnIndex": 2,
          "endRowIndex": 29,
          "sheetId": 661355791,
          "startColumnIndex": 1,
          "startRowIndex": 25
        }
      ],
      "properties": {
        "gridProperties": {
          "columnCount": 31,
          "rowCount": 1046
        },
        "index": 3,
        "sheetId": 661355791,
        "sheetType": "GRID",
        "title": "video"
      },
      "tables": [
        {
          "columnProperties": [
            {
              "columnName": "TOPIC"
            },
            {
              "columnIndex": 1,
              "columnName": "LESSON"
            },
            {
              "columnIndex": 2,
              "columnName": "動画"
            },
            {
              "columnIndex": 3,
              "columnName": "視聴状況"
            },
            {
              "columnIndex": 4,
              "columnName": "MEMO",
              "columnType": "TEXT"
            }
          ],
          "name": "C_Wave behaviour",
          "range": {
            "endColumnIndex": 17,
            "endRowIndex": 1,
            "sheetId": 661355791,
            "startColumnIndex": 12,
            "startRowIndex": 0
          },
          "rowsProperties": {
            "firstBandColorStyle": {
              "rgbColor": {
                "blue": 1,
                "green": 1,
                "red": 1
              }
            },
            "headerColorStyle": {
              "rgbColor": {
                "blue": 0.23529412,
                "green": 0.27450982,
                "red": 0.73333335
              }
            },
            "secondBandColorStyle": {
              "rgbColor": {
                "blue": 0.98039216,
                "green": 0.9764706,
                "red": 0.972549
              }
            }
          },
          "tableId": "137145717"
        },
        {
          "columnProperties": [
            {
              "columnName": "TOPIC"
            },
            {
              "columnIndex": 1,
              "columnName": "LESSON"
            },
            {
              "columnIndex": 2,
              "columnName": "動画"
            },
            {
              "columnIndex": 3,
              "columnName": "視聴状況"
            },
            {
              "columnIndex": 4,
              "columnName": "MEMO",
              "columnType": "TEXT"
            }
          ],
          "name": "A_Unity_and_diversity",
          "range": {
            "endColumnIndex": 5,
            "endRowIndex": 1,
            "sheetId": 661355791,
            "startColumnIndex": 0,
            "startRowIndex": 0
          },
          "rowsProperties": {
            "firstBandColorStyle": {
              "rgbColor": {
                "blue": 1,
                "green": 1,
                "red": 1
              }
            },
            "headerColorStyle": {
              "rgbColor": {
                "blue": 0.32941177,
                "green": 0.40784314,
                "red": 0.20784314
              }
            },
            "secondBandColorStyle": {
              "rgbColor": {
                "blue": 0.98039216,
                "green": 0.9764706,
                "red": 0.972549
              }
            }
          },
          "tableId": "2056664546"
        },
        {
          "columnProperties": [
            {
              "columnName": "TOPIC"
            },
            {
              "columnIndex": 1,
              "columnName": "LESSON"
            },
            {
              "columnIndex": 2,
              "columnName": "動画"
            },
            {
              "columnIndex": 3,
              "columnName": "視聴状況"
            },
            {
              "columnIndex": 4,
              "columnName": "MEMO",
              "columnType": "TEXT"
            }
          ],
          "name": "B_The particulate nature of matter",
          "range": {
            "endColumnIndex": 11,
            "endRowIndex": 1,
            "sheetId": 661355791,
            "startColumnIndex": 6,
            "startRowIndex": 0
          },
          "rowsProperties": {
            "firstBandColorStyle": {
              "rgbColor": {
                "blue": 1,
                "green": 1,
                "red": 1
              }
            },
            "headerColorStyle": {
              "rgbColor": {
                "blue": 0.75686276,
                "green": 0.37254903,
                "red": 0.3254902
              }
            },
            "secondBandColorStyle": {
              "rgbColor": {
                "blue": 0.98039216,
                "green": 0.9764706,
                "red": 0.972549
              }
            }
          },
          "tableId": "775306426"
        },
        {
          "columnProperties": [
            {
              "columnName": "TOPIC"
            },
            {
              "columnIndex": 1,
              "columnName": "LESSON"
            },
            {
              "columnIndex": 2,
              "columnName": "動画"
            },
            {
              "columnIndex": 3,
              "columnName": "視聴状況"
            },
            {
              "columnIndex": 4,
              "columnName": "MEMO",
              "columnType": "TEXT"
            }
          ],
          "name": "D_Fields",
          "range": {
            "endColumnIndex": 23,
            "endRowIndex": 1,
            "sheetId": 661355791,
            "startColumnIndex": 18,
            "startRowIndex": 0
          },
          "rowsProperties": {
            "firstBandColorStyle": {
              "rgbColor": {
                "blue": 1,
                "green": 1,
                "red": 1
              }
            },
            "headerColorStyle": {
              "rgbColor": {
                "blue": 0.25882354,
                "green": 0.21176471,
                "red": 0.60784316
              }
            },
            "secondBandColorStyle": {
              "rgbColor": {
                "blue": 0.98039216,
                "green": 0.9764706,
                "red": 0.972549
              }
            }
          },
          "tableId": "793604491"
        }
      ]
    }
  ],
  "spreadsheetId": "1XR6pdZc23fijgYmjKZ0gcqU57iHsmRdfzmZHVQYGyNg",
  "spreadsheetUrl": "https://docs.google.com/spreadsheets/d/1XR6pdZc23fijgYmjKZ0gcqU57iHsmRdfzmZHVQYGyNg/edit?ouid=111863040728288757718"
}
